onetap/Authentication.py
onetap/__init__.py
onetap-1.0.0b2.dist-info/LICENSE.md
onetap-1.0.0b2.dist-info/METADATA
onetap-1.0.0b2.dist-info/WHEEL
onetap-1.0.0b2.dist-info/top_level.txt
onetap-1.0.0b2.dist-info/RECORD
